demo/__init__.py
demo/__main__.py
demo/config.toml
demo/hello_world.py
demo/run_similarity_pipeline.py
demo/stopwords/README
demo/stopwords/arabic
demo/stopwords/azerbaijani
demo/stopwords/basque
demo/stopwords/bengali
demo/stopwords/catalan
demo/stopwords/chinese
demo/stopwords/danish
demo/stopwords/dutch
demo/stopwords/english
demo/stopwords/finnish
demo/stopwords/french
demo/stopwords/german
demo/stopwords/greek
demo/stopwords/hebrew
demo/stopwords/hinglish
demo/stopwords/hungarian
demo/stopwords/indonesian
demo/stopwords/italian
demo/stopwords/kazakh
demo/stopwords/nepali
demo/stopwords/norwegian
demo/stopwords/portuguese
demo/stopwords/romanian
demo/stopwords/russian
demo/stopwords/slovene
demo/stopwords/spanish
demo/stopwords/swedish
demo/stopwords/tajik
demo/stopwords/turkish
conExtraction-0.0.3.dist-info/LICENSE
conExtraction-0.0.3.dist-info/METADATA
conExtraction-0.0.3.dist-info/WHEEL
conExtraction-0.0.3.dist-info/entry_points.txt
conExtraction-0.0.3.dist-info/top_level.txt
conExtraction-0.0.3.dist-info/RECORD
