Metadata-Version: 2.1
Name: conExtraction
Version: 0.0.3
Summary: Extract the conversation
Author-email: Vincent Yun <clouddt@gmail.com>
License: The MIT License (MIT)
Project-URL: Homepage, https://github.com/conextraction/demo
Keywords: feed,conversation,extraction
Classifier: License :: OSI Approved :: MIT License
Classifier: Programming Language :: Python
Classifier: Programming Language :: Python :: 3
Requires-Python: >=3.6
License-File: LICENSE
Provides-Extra: dev
Requires-Dist: black ; extra == 'dev'
Requires-Dist: bumpver ; extra == 'dev'
Requires-Dist: isort ; extra == 'dev'
Requires-Dist: pip-tools ; extra == 'dev'
Requires-Dist: pytest ; extra == 'dev'
